Graphics/Filters.py
Graphics/__init__.py
NephLib-0.0.1.dist-info/LICENSE
NephLib-0.0.1.dist-info/METADATA
NephLib-0.0.1.dist-info/WHEEL
NephLib-0.0.1.dist-info/top_level.txt
NephLib-0.0.1.dist-info/RECORD
